datapatch/__init__.py
datapatch/exc.py
datapatch/lookup.py
datapatch/option.py
datapatch/py.typed
datapatch/result.py
datapatch/util.py
datapatch-1.2.4.dist-info/METADATA
datapatch-1.2.4.dist-info/WHEEL
datapatch-1.2.4.dist-info/licenses/LICENSE
datapatch-1.2.4.dist-info/RECORD
