Metadata-Version: 2.4
Name: datapatch
Version: 1.2.4
Summary: A library for defining rule-based overrides on messy data.
Project-URL: Homepage, https://github.com/opensanctions/datapatch
Author-email: OpenSanctions <info@opensanctions.org>
License: MIT
License-File: LICENSE
Classifier: Intended Audience :: Developers
Classifier: License :: OSI Approved :: MIT License
Classifier: Operating System :: OS Independent
Classifier: Programming Language :: Python :: 3.9
Classifier: Programming Language :: Python :: 3.10
Classifier: Programming Language :: Python :: 3.11
Classifier: Programming Language :: Python :: 3.12
Classifier: Programming Language :: Python :: 3.13
Requires-Python: >=3.9
Requires-Dist: babel>=2.9.1
Requires-Dist: normality>=2.1.1
Requires-Dist: pyyaml
Provides-Extra: dev
Requires-Dist: black; extra == 'dev'
Requires-Dist: build; extra == 'dev'
Requires-Dist: bump2version; extra == 'dev'
Requires-Dist: flake8; extra == 'dev'
Requires-Dist: isort; extra == 'dev'
Requires-Dist: mypy; extra == 'dev'
Requires-Dist: pytest; extra == 'dev'
Requires-Dist: pytest-cov; extra == 'dev'
Requires-Dist: types-pyyaml; extra == 'dev'
Requires-Dist: wheel; extra == 'dev'
